gliclass/__init__.py
gliclass/config.py
gliclass/data_processing.py
gliclass/layers.py
gliclass/loss_functions.py
gliclass/model.py
gliclass/pipeline.py
gliclass/poolings.py
gliclass/scorers.py
gliclass/training.py
gliclass/utils.py
gliclass-0.1.14.dist-info/METADATA
gliclass-0.1.14.dist-info/WHEEL
gliclass-0.1.14.dist-info/licenses/LICENSE
gliclass-0.1.14.dist-info/RECORD
