Metadata-Version: 2.4
Name: gliclass
Version: 0.1.14
Summary: Generalist and Lightweight Model for Text Classification
License-File: LICENSE
Author: knowledgator.com
Requires-Python: >=3.9,<4.0
Classifier: Programming Language :: Python :: 3
Classifier: Programming Language :: Python :: 3.9
Classifier: Programming Language :: Python :: 3.10
Classifier: Programming Language :: Python :: 3.11
Classifier: Programming Language :: Python :: 3.12
Classifier: Programming Language :: Python :: 3.13
Classifier: Programming Language :: Python :: 3.14
Requires-Dist: numpy (>=2.0.0,<3.0.0)
Requires-Dist: scikit-learn (>=1.0.0,<2.0.0)
Requires-Dist: torch (>=2.0.0,<3.0.0)
Requires-Dist: transformers (>=4.57.3)
